watched_kodi/KodiAddon.py
watched_kodi/__init__.py
watched_kodi/common.py
watched_kodi/watched_local.py
watched_kodi/xbmc.py
watched_kodi/xbmcaddon.py
watched_kodi/xbmcgui.py
watched_kodi/xbmcplugin.py
watched_kodi/xbmcvfs.py
watched_kodi-0.0.0.dist-info/METADATA
watched_kodi-0.0.0.dist-info/WHEEL
watched_kodi-0.0.0.dist-info/top_level.txt
watched_kodi-0.0.0.dist-info/RECORD
